CMakeLists.txt
LICENSE
MANIFEST.in
README.md
pyproject.toml
setup.cfg
setup.py
lib/IntervalTree.h
lib/pybind11/CMakeLists.txt
lib/pybind11/include/pybind11/attr.h
lib/pybind11/include/pybind11/buffer_info.h
lib/pybind11/include/pybind11/cast.h
lib/pybind11/include/pybind11/chrono.h
lib/pybind11/include/pybind11/common.h
lib/pybind11/include/pybind11/complex.h
lib/pybind11/include/pybind11/eigen.h
lib/pybind11/include/pybind11/embed.h
lib/pybind11/include/pybind11/eval.h
lib/pybind11/include/pybind11/functional.h
lib/pybind11/include/pybind11/iostream.h
lib/pybind11/include/pybind11/numpy.h
lib/pybind11/include/pybind11/operators.h
lib/pybind11/include/pybind11/options.h
lib/pybind11/include/pybind11/pybind11.h
lib/pybind11/include/pybind11/pytypes.h
lib/pybind11/include/pybind11/stl.h
lib/pybind11/include/pybind11/stl_bind.h
lib/pybind11/include/pybind11/detail/class.h
lib/pybind11/include/pybind11/detail/common.h
lib/pybind11/include/pybind11/detail/descr.h
lib/pybind11/include/pybind11/detail/init.h
lib/pybind11/include/pybind11/detail/internals.h
lib/pybind11/include/pybind11/detail/typeid.h
lib/pybind11/tests/CMakeLists.txt
lib/pybind11/tests/test_cmake_build/CMakeLists.txt
lib/pybind11/tests/test_cmake_build/installed_embed/CMakeLists.txt
lib/pybind11/tests/test_cmake_build/installed_function/CMakeLists.txt
lib/pybind11/tests/test_cmake_build/installed_target/CMakeLists.txt
lib/pybind11/tests/test_cmake_build/subdirectory_embed/CMakeLists.txt
lib/pybind11/tests/test_cmake_build/subdirectory_function/CMakeLists.txt
lib/pybind11/tests/test_cmake_build/subdirectory_target/CMakeLists.txt
lib/pybind11/tests/test_embed/CMakeLists.txt
lib/pybind11/tools/FindCatch.cmake
lib/pybind11/tools/FindEigen3.cmake
lib/pybind11/tools/FindPythonLibsNew.cmake
lib/pybind11/tools/pybind11Tools.cmake
src/pinetree/__init__.py
src/pinetree/averager.py
src/pinetree/batch.py
src/pinetree/choices.cpp
src/pinetree/choices.hpp
src/pinetree/event_signal.hpp
src/pinetree/feature.cpp
src/pinetree.egg-info/PKG-INFO
src/pinetree.egg-info/SOURCES.txt
src/pinetree.egg-info/dependency_links.txt
src/pinetree.egg-info/not-zip-safe
src/pinetree.egg-info/top_level.txt
