Metadata-Version: 2.1
Name: pinetree
Version: 0.4.0
Summary: stochastic simulation of gene expression with site-specific translation rates
Home-page: https://github.com/clauswilke/pinetree
Author: Benjamin Jack
Author-email: benjamin.r.jack@gmail.com
License: MIT
Download-URL: https://github.com/clauswilke/pinetree/archive/v0.4.0.tar.gz
Keywords: gene,codon,transcription,translation,biology,stochastic
Platform: UNKNOWN
